chess_pairings/__init__.py
chess_pairings/__init__.pyi
chess_pairings/_classify.py
chess_pairings/_types.py
chess_pairings/mapping.py
chess_pairings-0.3.0.dist-info/METADATA
chess_pairings-0.3.0.dist-info/WHEEL
chess_pairings-0.3.0.dist-info/top_level.txt
chess_pairings-0.3.0.dist-info/RECORD
